{
    "Gross_domestic_product_(GDP)": "SDG_08_10?unit=CLV10_EUR_HAB",
    "Mobile_students_from_abroad": "EDUC_UOE_MOBS04?iscedf13=F01&iscedf13=F02&iscedf13=F03&iscedf13=F04&iscedf13=F05&iscedf13=F0511&iscedf13=F0512&iscedf13=F052&iscedf13=F053&iscedf13=F054&iscedf13=F06&iscedf13=F07&iscedf13=F071&iscedf13=F072&iscedf13=F073&iscedf13=F08&iscedf13=F09&iscedf13=F091&iscedf13=F0911&iscedf13=F092&iscedf13=F0921&iscedf13=F0922&iscedf13=F0923&iscedf13=F10&iscedf13=F1011&iscedf13=F1012&iscedf13=F1013&iscedf13=F1014&iscedf13=F1015&iscedf13=F104",
    "Youth_participation_in_cultural_activities_2015": "",
    "Youth_population": "",
    "Mean_monthly_earnings_2018": "",
    "Harmonised_index_consumer_prices": "",
    "House_price_index": "",
    "Crime_violence_and_vandalism": "",
    "Employment_expectations_indicator": "",
    "Employment_rates_by_sex_and_citizenship": "",
    "Employment_rates_by_sex": "",
    "Median_net_income_by_age": "",
    "Expenditure_on_education_as_percent_of_GDP": "",
    "Electricity_prices_for_household_consumers": "",
    "Gas_prices_for_household_consumers": "",
    "General_government_expenditure_by_sector": "",
    "Gross_domestic_expenditure_on_R&D_by_sector": "",
    "R&D_personnel_by_sector_field_and_sex": "",
    "Share_of_Government_Budget_Allocations_in_R&D": ""
}